README.rst
setup.py
decmoc/__init__.py
decmoc/registry.py
decmoc.egg-info/PKG-INFO
decmoc.egg-info/SOURCES.txt
decmoc.egg-info/dependency_links.txt
decmoc.egg-info/requires.txt
decmoc.egg-info/top_level.txt
decmoc/test/__init__.py
decmoc/test/test_registry.py