Metadata-Version: 1.1
Name: decmoc
Version: 20130206
Summary: Declarative mocking
Home-page: https://github.com/lvh/decmoc
Author: Laurens Van Houtven
Author-email: _@lvh.cc
License: ISC
Platform: UNKNOWN
Classifier: Development Status :: 3 - Alpha
Classifier: Framework :: Twisted
Classifier: License :: OSI Approved :: ISC License (ISCL)
